faq/__init__.py
faq/admin.py
faq/apps.py
faq/models.py
faq/urls.py
faq/version.py
faq/views.py
faq/migrations/0001_initial.py
faq/migrations/0002_alter_abstract_type.py
faq/migrations/0003_update_translations.py
faq/migrations/__init__.py
django_fluo_faq-0.1.dist-info/AUTHORS
django_fluo_faq-0.1.dist-info/COPYING
django_fluo_faq-0.1.dist-info/METADATA
django_fluo_faq-0.1.dist-info/WHEEL
django_fluo_faq-0.1.dist-info/top_level.txt
django_fluo_faq-0.1.dist-info/RECORD
